wave_rover_serial/__init__.py
wave_rover_serial/robot.py
wave_rover_serial-0.5.dist-info/LICENSE.txt
wave_rover_serial-0.5.dist-info/METADATA
wave_rover_serial-0.5.dist-info/WHEEL
wave_rover_serial-0.5.dist-info/top_level.txt
wave_rover_serial-0.5.dist-info/RECORD
