Metadata-Version: 2.1
Name: wave_rover_serial
Version: 0.5
Summary: A package to simplify the wave rover serial communication
Home-page: https://github.com/msanterre/wave_rover_serial
Author: Maxime Santerre
Author-email: maxime.santerre@chime.com
Requires-Python: >=3.8
License-File: LICENSE.txt
Requires-Dist: pyserial >=3.4
